arithmetics/__init__.py
arithmetics/arithmetics.py
arithmetics/test/__init__.py
arithmetics/test/test.py
arithmetics-0.2.0.dist-info/LICENSE
arithmetics-0.2.0.dist-info/METADATA
arithmetics-0.2.0.dist-info/WHEEL
arithmetics-0.2.0.dist-info/top_level.txt
arithmetics-0.2.0.dist-info/RECORD
