Metadata-Version: 2.1
Name: arithmetics
Version: 0.2.0
Summary: Python arithmetics for very long numbers.
Home-page: https://github.com/oebilgen/arithmetics
Author: Ozan Eren Bilgen
Author-email: oebilgen@gmail.com
License: MIT
Keywords: arithmetic math floating point multiplication subtraction addition precision decimal rounding
Platform: UNKNOWN
